{
    "events": [
        {
            "id": "213213",
            "title": "make the illustraton unique and let it be the center of the design",
            "date": "thu, 19 may 2022",
            "author": "Pablo Stanley",
            "jobRole": "Art Director & Illustrator",
            "img": "/illustrations/user-avatar/elliot-avatar-minified.svg"
        },
        {
            "id": "211233",
            "title": "make the illustraton unique and let it be the center of the design",
            "date": "thu, 19 may 2022",
            "author": "Pablo Stanley",
            "jobRole": "Art Director & Illustrator",
            "img": "/illustrations/user-avatar/olive-avatar-minified.svg"
        },
        {
            "id": "211423",
            "title": "make the illustraton unique and let it be the center of the design",
            "date": "thu, 19 may 2022",
            "author": "Pablo Stanley",
            "jobRole": "Art Director & Illustrator",
            "img": "/illustrations/user-avatar/thomas-avatar-minified.svg"
        }
    ]
}